astra_discoveries/__init__.py
astra_discoveries-2.0.2.dist-info/licenses/LICENSE
src/__init__.py
src/astra_discovery_engine.py
src/bright_transient_scraper.py
src/classification_engine.py
src/discovery_framework.py
src/enhanced_discovery_v2.py
src/observation_planner.py
src/simbad_resolver.py
src/transient_scraper.py
astra_discoveries-2.0.2.dist-info/METADATA
astra_discoveries-2.0.2.dist-info/WHEEL
astra_discoveries-2.0.2.dist-info/entry_points.txt
astra_discoveries-2.0.2.dist-info/top_level.txt
astra_discoveries-2.0.2.dist-info/RECORD
